{
  "id": "black_myth_wukong",
  "name": "Black Myth: Wukong",
  "language": "de",
  "type": "base",
  "keywords": [
    "black myth wukong",
    "black myth: wukong",
    "black myth",
    "wukong"
  ],
  "system_prompt": "Du bist ein erfahrener Echtzeit-Coach für Black Myth: Wukong. Analysiere den Screenshot (HUD, Minimap, Inventar, Gegner, Menüs) und gib sofort einen konkreten, umsetzbaren Tipp zur aktuellen Situation. Beziehe dich auf sichtbare Elemente und nenne die nächste beste Aktion. Nutze das unten bereitgestellte Spielwissen und respektiere die Spoiler-Vorgaben – verrate nichts über den sichtbaren Fortschritt hinaus.",
  "additional_context": "Spielwissen (base):\n{\n  \"rank\": 1,\n  \"title\": \"Black Myth: Wukong\",\n  \"metacritic_score\": 81,\n  \"last_updated\": \"2026-03-31\",\n  \"sections\": {\n    \"cheats\": {\n      \"description\": \"Trainer und Cheats für PC\",\n      \"items\": [\n        {\n          \"name\": \"FLiNG Trainer\",\n          \"features\": [\n            \"God Mode / Ignore Hits\",\n            \"Infinite Health\",\n            \"Infinite Mana\",\n            \"Infinite Stamina\",\n            \"Max Focus\",\n            \"Infinite Qi\",\n            \"Max Attack/Defense/Crit Rate\",\n            \"One Hit Kill\",\n            \"Super Speed\",\n            \"Slow Motion\"\n          ],\n          \"source\": \"https://flingtrainer.com\"\n        },\n        {\n          \"name\": \"TrainersBase\",\n          \"features\": [\n            \"35+ Cheat Optionen\",\n            \"Unendlich Geist (Will)\",\n            \"Super Angriffsgeschwindigkeit\",\n            \"Unendlich Gourd (Heiltrank)\"\n          ],\n          \"source\": \"https://trainersbase.com\"\n        },\n        {\n          \"note\": \"Für PS5 gibt es KEINE nativen Cheats - nur PC-Trainer verfügbar\"\n        }\n      ]\n    },\n    \"builds\": {\n      \"description\": \"Beste Builds und Ausrüstungen\",\n      \"early_game\": [\n        {\n          \"name\": \"Crushing Gale Staff Build\",\n          \"armor\": \"Gale Guardian Set (Kapitel 1)\",\n          \"weapon\": \"Crushing Gale Staff\",\n          \"focus\": \"Hoher Spirit-Skill-Damage\",\n          \"tips\": \"Sammle alle Materialien in der Schwarzer Wind Region\"\n        }\n      ],\n      \"mid_game\": [\n        {\n          \"name\": \"Dasheng Set + Golden Loong Staff\",\n          \"armor\": \"Gold Exoskeleton Set\",\n          \"weapon\": \"Golden Loong Staff\",\n          \"curios\": \"Fatal Destruction, Tiger Talisman\",\n          \"focus\": \"Balanciertes Spiel mit gutem Crit-Damage\"\n        }\n      ],\n      \"late_game\": [\n        {\n          \"name\": \"Supreme Monkey King Build\",\n          \"armor\": \"Gold Suozi Set (Post-Game optional)\",\n          \"weapon\": \"Ruyi Jingu Bang Staff (Endboss-Potenzial)\",\n          \"curios\": \"Beste Kombination aus Crit-Chance, Will-Regen\",\n          \"wards\": \"Willbender Set zur Will-Rückgewinnung\"\n        }\n      ],\n      \"best_spirits\": [\n        \"Gold Armored Rhino - Best Defensiv Spirit\",\n        \"Red Tides - Hoher Serien-Damage\",\n        \"Azure Dust - AOE Freeze\",\n        \"Wandering Wight - Starker Smasher\"\n      ]\n    },\n    \"bosses\": {\n      \"secret_bosses\": [\n        {\n          \"name\": \"Elder Jinchi\",\n          \"chapter\": 1,\n          \"location\": \"Nebenquest - alter Tempel\",\n          \"reward\": \"Goldenes Harz, Will-Boost\",\n          \"hint\": \"Sprich mit allen NPCs in Kapitel 1\"\n        },\n        {\n          \"name\": \"Mad Tiger\",\n          \"chapter\": 2,\n          \"location\": \"Sandgate Village - versteckte Kammer\",\n          \"reward\": \"Klaue des Beißers (Upgrade-Material)\",\n          \"hint\": \"Erfordert Qi-Transformation um Zugang zu bekommen\"\n        },\n        {\n          \"name\": \"Yellow Loong (HP Mechanik Boss)\",\n          \"chapter\": 4,\n          \"location\": \"Das Net aus Seiden\",\n          \"reward\": \"Loong Scale für Golden Loong Staff\",\n          \"hint\": \"Sehr schwer, empfohlen ab Level 60\"\n        },\n        {\n          \"name\": \"Arete of the Holy Mountain\",\n          \"chapter\": 5,\n          \"location\": \"Mount Huaguo Secret\",\n          \"reward\": \"Einzigartiges Curio\",\n          \"hint\": \"Erfordert New Game+ oder bestimmte Quest-Completion\"\n        }\n      ],\n      \"hardest_bosses_ranked\": [\n        \"Bull King (Final) - Hohe HP, zweite Phase brutal\",\n        \"Tiger Vanguard - Schnell und aggressiv\",\n        \"Yellow Wind Sage - Special Mechaniken\",\n        \"Immortal Guardians - Zwei Boss-Kämpfe gleichzeitig\"\n      ]\n    },\n    \"secrets\": {\n      \"description\": \"Versteckte Inhalte und Mechaniken\",\n      \"items\": [\n        {\n          \"name\": \"Vier verzauberte Höfe\",\n          \"details\": \"Finde alle 4 versteckten Portale für exklusive Rüstungssets\",\n          \"chapter\": \"Kapitel 2-4 verteilt\"\n        },\n        {\n          \"name\": \"Schmiede-System\",\n          \"details\": \"Nicht alle NPCs schmieden - manche brauchen besondere Materialien die überall versteckt sind\",\n          \"tips\": \"Nutze Immobilize Spell auf NPCs um Town zu sichern\"\n        },\n        {\n          \"name\": \"Shrine Fast Travel\",\n          \"details\": \"Buddha-Statuen als Checkpoints - aber nicht alle sind im Story-Pfad!\",\n          \"exploration\": \"Immer in Seitengänge schauen\"\n        },\n        {\n          \"name\": \"NPC Quest Chains\",\n          \"details\": \"Zhu Bajie, der Schweine-Dämon hat eigene Questline mit Belohnungen\",\n          \"reward\": \"Exklusive Transformation\"\n        },\n        {\n          \"name\": \"Heiligtümer (Relics)\",\n          \"details\": \"6 Holy Relics sammelbar - jeder gibt permanente Stats\",\n          \"missable\": true\n        }\n      ]\n    },\n    \"tips\": {\n      \"startup\": [\n        \"Sammle ALLE Spirit-Beutel (auch schwache) - piercings stack\",\n        \"Upgrade deinen Gourd IMMER sofort beim Schmied\",\n        \"Heilung regeneriert sich NICHT automatisch - Items sparen für Bosskämpfe\",\n        \"Cool Down Management: Spells haben lange CD - timing ist alles\"\n      ],\n      \"combat\": [\n        \"Stance Switching: Heavy/Thrust Stance für Boss-Knockdowns\",\n        \"Focus Points generieren durch perfektes Dodgen und light attacks\",\n        \"Transformationen sind Ressourcen - nicht einfach verbrauchen\",\n        \"Staff Spin (Trie): Perfekt für Projektile und AOE\"\n      ],\n      \"exploration\": [\n        \"Keine Minimap - Umgebung merken oder Notizen machen\",\n        \"Goldene Käfer geben Will-Punkte - ALLE sammeln\",\n        \"Höhlen haben oft Side-Bosse mit Materialien\",\n        \"NPCs haben markante Farben - ansprechen!\"\n      ],\n      \"leveling\": [\n        \"Will ist XP - beim Sterben verlieren durch Wiederbelebung\",\n        \"Spark (Skill-Punkte) werden beim Neusetzen zurückerstattet\",\n        \"Stat-Investition vor Bossen: Will und Focus zuerst\"\n      ]\n    },\n    \"difficulty\": {\n      \"rating\": \"Soulslike - Herausfordernd\",\n      \"death_penalty\": \"Verlust von Will-Punkten beim Wiederbeleben\",\n      \"assist_mode\": false,\n      \"dlc_difficulty\": \"Shadow of the Erdtree Level optional\"\n    }\n  },\n  \"sources\": [\n    \"https://flingtrainer.com\",\n    \"https://rockpapershotgun.com\",\n    \"https://gamingbolt.com\",\n    \"https://ign.com/wikis\",\n    \"https://maxroll.gg\"\n  ]\n}",
  "platforms": [
    "PC",
    "PS5",
    "Xbox Series X/S"
  ]
}
